rapidwright/__init__.py
rapidwright/rapidwright.py
rapidwright-2025.1.3.dist-info/LICENSE.TXT
rapidwright-2025.1.3.dist-info/METADATA
rapidwright-2025.1.3.dist-info/WHEEL
rapidwright-2025.1.3.dist-info/entry_points.txt
rapidwright-2025.1.3.dist-info/top_level.txt
rapidwright-2025.1.3.dist-info/RECORD
