Metadata-Version: 2.1
Name: rapidwright
Version: 2025.1.3
Summary: Xilinx RapidWright Framework Wrapped for Python.
Home-page: https://github.com/Xilinx/RapidWright
Author: Chris Lavin
Author-email: chris.lavin@amd.com
License: Apache 2.0 and Others
Project-URL: Changelog, https://github.com/Xilinx/RapidWright/blob/master/RELEASE_NOTES.TXT
Project-URL: Issue Tracker, https://github.com/Xilinx/RapidWright/issues
Keywords: rapidwright,xilinx,fpga,design checkpoint,DCP,placement,routing
Classifier: Operating System :: Unix
Classifier: Operating System :: POSIX
Classifier: Operating System :: Microsoft :: Windows
Classifier: Programming Language :: Python
Classifier: Programming Language :: Python :: 3
Classifier: Programming Language :: Python :: 3.5
Classifier: Programming Language :: Python :: 3.6
Classifier: Programming Language :: Python :: 3.7
Classifier: Programming Language :: Python :: 3.8
Classifier: Programming Language :: Python :: 3.9
Classifier: Topic :: Utilities
Requires-Python: !=3.0.*, !=3.1.*, !=3.2.*, !=3.3.*, !=3.4.*
License-File: LICENSE.TXT
Requires-Dist: jpype1
